<?xml version="1.0" encoding="utf-8"?>
<Dependencies>
  <ToolsetDependencies>
    <Dependency Name="Microsoft.DotNet.Arcade.Sdk" Version="7.0.0-beta.21608.1">
      <Uri>https://github.com/dotnet/arcade</Uri>
      <Sha>200adbc809c4451973d1929a53a75502b7cada01</Sha>
      <SourceBuild RepoName="arcade" ManagedOnly="true" />
    </Dependency>
    <Dependency Name="Microsoft.SourceBuild.Intermediate.source-build-reference-packages" Version="6.0.0-servicing.22302.1">
      <Uri>https://github.com/dotnet/source-build-reference-packages</Uri>
      <Sha>6eb1f46c315e850c8ac318fa56a0f3e05c2214c5</Sha>
      <SourceBuild RepoName="source-build-reference-packages" ManagedOnly="true" />
    </Dependency>
  </ToolsetDependencies>
</Dependencies>
